{"elapsed":"0.475","endpoint-url":"https://www.registers.service.gov.uk/registers/field/download-csv","entry-date":"2021-02-15T00:50:03.002338","request-headers":{"Accept":"*/*","Accept-Encoding":"gzip, deflate","Connection":"keep-alive","Cookie":"seen_cookie_message=true","User-Agent":"Digital Land"},"resource":"89be2b04f644f8918bcb3a30dc19491c122d7fc67f3b3130bd55bb45cf36e418","response-headers":{"Cache-Control":"private","Connection":"keep-alive","Content-Disposition":"attachment; filename=field.csv","Content-Transfer-Encoding":"binary","Content-Type":"application/csv; header=present","Date":"Mon, 15 Feb 2021 00:50:04 GMT","ETag":"W/\"89be2b04f644f8918bcb3a30dc19491c\"","Referrer-Policy":"strict-origin-when-cross-origin","Set-Cookie":"seen_cookie_message=true; path=/; expires=Tue, 15 Feb 2022 00:50:04 GMT","Strict-Transport-Security":"max-age=31536000; includeSubDomains; preload","Transfer-Encoding":"chunked","Via":"1.1 c57d1eb27f41d3e95fc5060845849c06.cloudfront.net (CloudFront)","X-Amz-Cf-Id":"wMpgn5W30wNgWFzn4ndpquPauzM6O-CiOXLclPAqV12itSapGigDmw==","X-Amz-Cf-Pop":"IAD50-C2","X-Cache":"Miss from cloudfront","X-Content-Type-Options":"nosniff","X-Download-Options":"noopen","X-Frame-Options":"SAMEORIGIN","X-Permitted-Cross-Domain-Policies":"none","X-Request-Id":"393b512a-102b-4e88-b659-b9ab15c8738d","X-Runtime":"0.066443","X-Vcap-Request-Id":"d8165747-98ba-43ec-6fe8-da0d476a0327","X-Xss-Protection":"1; mode=block"},"ssl-verify":true,"status":"200"}